riddle_handler/__init__.py
riddle_handler/check_answer.py
riddle_handler/generate_riddle.py
riddle_handler/provide_hint.py
riddle_handler/read_file.py
riddle_handler/submit_riddle.py
riddle_handler-1.0.4.dist-info/LICENSE
riddle_handler-1.0.4.dist-info/METADATA
riddle_handler-1.0.4.dist-info/WHEEL
riddle_handler-1.0.4.dist-info/top_level.txt
riddle_handler-1.0.4.dist-info/RECORD
