Metadata-Version: 2.1
Name: riddle-handler
Version: 1.0.4
Summary: A Python package for managing and interacting with a JSON-based riddle library.
Author-email: code crafters <bw2176@nyu.edu>
License: MIT
Keywords: riddle,library,JSON,file handling
Classifier: Programming Language :: Python :: 3
Classifier: License :: OSI Approved :: MIT License
Classifier: Operating System :: OS Independent
License-File: LICENSE
Requires-Dist: pytest
